
[{"tag_value":"Politics","party":"ALP","number":"40"},{"tag_value":"Social Issues","party":"National","number":"39"},{"tag_value":"Education","party":"ALP","number":"33"},{"tag_value":"Education","party":"National","number":"27"},{"tag_value":"Environment","party":"National","number":"21"},{"tag_value":"Politics","party":"National","number":"20"},{"tag_value":"Disaster_Accident","party":"National","number":"19"},{"tag_value":"Business_Finance","party":"National","number":"17"},{"tag_value":"Politics","party":"Liberal","number":"13"},{"tag_value":"Human Interest","party":"National","number":"11"},{"tag_value":"Environment","party":"Liberal","number":"10"},{"tag_value":"Health_Medical_Pharma","party":"National","number":"9"},{"tag_value":"Social Issues","party":"ALP","number":"9"},{"tag_value":"Law_Crime","party":"ALP","number":"9"},{"tag_value":"Business_Finance","party":"Liberal","number":"8"},{"tag_value":"Hospitality_Recreation","party":"National","number":"8"},{"tag_value":"Law_Crime","party":"National","number":"8"},{"tag_value":"Labor","party":"ALP","number":"8"},{"tag_value":"Education","party":"Liberal","number":"7"},{"tag_value":"Social Issues","party":"Liberal","number":"7"},{"tag_value":"Disaster_Accident","party":"Liberal","number":"6"},{"tag_value":"Business_Finance","party":"ALP","number":"6"},{"tag_value":"Technology_Internet","party":"Liberal","number":"5"},{"tag_value":"Technology_Internet","party":"National","number":"5"},{"tag_value":"Entertainment_Culture","party":"Liberal","number":"4"},{"tag_value":"Disaster_Accident","party":"ALP","number":"3"},{"tag_value":"Law_Crime","party":"Liberal","number":"3"},{"tag_value":"Politics","party":"Greens","number":"3"},{"tag_value":"Human Interest","party":"Liberal","number":"3"},{"tag_value":"Health_Medical_Pharma","party":"Liberal","number":"3"},{"tag_value":"Law_Crime","party":"Greens","number":"2"},{"tag_value":"Labor","party":"Liberal","number":"2"},{"tag_value":"Entertainment_Culture","party":"ALP","number":"2"},{"tag_value":"Labor","party":"National","number":"2"},{"tag_value":"Hospitality_Recreation","party":"Liberal","number":"2"},{"tag_value":"Entertainment_Culture","party":"National","number":"2"},{"tag_value":"Religion_Belief","party":"National","number":"2"},{"tag_value":"Education","party":"Greens","number":"2"},{"tag_value":"Social Issues","party":"Greens","number":"2"},{"tag_value":"War_Conflict","party":"Liberal","number":"1"},{"tag_value":"Sports","party":"National","number":"1"},{"tag_value":"War_Conflict","party":"National","number":"1"},{"tag_value":"Entertainment_Culture","party":"Greens","number":"1"},{"tag_value":"Hospitality_Recreation","party":"Greens","number":"1"},{"tag_value":"Religion_Belief","party":"Liberal","number":"1"},{"tag_value":"Health_Medical_Pharma","party":"Greens","number":"1"},{"tag_value":"Environment","party":"ALP","number":"1"},{"tag_value":"Disaster_Accident","party":"Greens","number":"1"},{"tag_value":"Environment","party":"Greens","number":"1"},{"tag_value":"Labor","party":"Greens","number":"1"}]